yta_image_advanced/__init__.py
yta_image_advanced/edition/__init__.py
yta_image_advanced/edition/editor.py
yta_image_advanced/experimental/__init__.py
yta_image_advanced/experimental/download/__init__.py
yta_image_advanced/experimental/download/bing.py
yta_image_advanced/experimental/download/image_searcher.py
yta_image_advanced/generation/__init__.py
yta_image_advanced/generation/reviews/__init__.py
yta_image_advanced/generation/reviews/tripadvisor/__init__.py
yta_image_advanced/generation/reviews/tripadvisor/generator.py
yta_image_advanced/generation/rrss/__init__.py
yta_image_advanced/generation/rrss/discord/__init__.py
yta_image_advanced/generation/rrss/youtube/__init__.py
yta_image_advanced/greenscreen/__init__.py
yta_image_advanced/greenscreen/remover.py
yta_image_advanced/mask/__init__.py
yta_image_advanced/mask/presets.py
yta_image_advanced-0.0.8.dist-info/LICENSE
yta_image_advanced-0.0.8.dist-info/METADATA
yta_image_advanced-0.0.8.dist-info/WHEEL
yta_image_advanced-0.0.8.dist-info/RECORD
