Metadata-Version: 2.3
Name: yta-image-advanced
Version: 0.0.8
Summary: Youtube Autonomous Image Advanced Module.
Author: danialcala94
Author-email: danielalcalavalera@gmail.com
Requires-Python: ==3.9
Classifier: Programming Language :: Python :: 3
Classifier: Programming Language :: Python :: 3.9
Requires-Dist: pillow-lut (>=1.0.1,<2.0.0)
Requires-Dist: scikit-image (>=0.22.0,<9.0.0)
Requires-Dist: yta_constants (>=0.0.1,<1.0.0)
Requires-Dist: yta_file (>=0.0.1,<1.0.0)
Requires-Dist: yta_file_downloader (>=0.0.1,<1.0.0)
Requires-Dist: yta_general (>=0.0.1,<1.0.0)
Requires-Dist: yta_image_base (>=0.0.1,<1.0.0)
Requires-Dist: yta_programming (>=0.0.1,<1.0.0)
Requires-Dist: yta_validation (>=0.0.1,<1.0.0)
Requires-Dist: yta_web_scraper (>=0.0.1,<1.0.0)
